deadline_docker_submission/__init__.py
deadline_docker_submission/__version__.py
deadline_docker_submission/main.py
deadline_docker_submission-0.2.4.dist-info/LICENSE.txt
deadline_docker_submission-0.2.4.dist-info/METADATA
deadline_docker_submission-0.2.4.dist-info/WHEEL
deadline_docker_submission-0.2.4.dist-info/entry_points.txt
deadline_docker_submission-0.2.4.dist-info/top_level.txt
deadline_docker_submission-0.2.4.dist-info/RECORD
